.bumpversion.cfg
.dockerignore
.gitignore
CHANGELOG.md
Dockerfile
MANIFEST.in
README.rst
justfile
requirements-dev.txt
requirements-flake8.txt
requirements.txt
setup.py
template-version.txt
test.sh
tox.ini
src/fhs_enyaq_data/__init__.py
src/fhs_enyaq_data/__version__.py
src/fhs_enyaq_data/abrp_list_cars.py
src/fhs_enyaq_data/abrp_send.py
src/fhs_enyaq_data/cli.py
src/fhs_enyaq_data/config.py
src/fhs_enyaq_data/fhs_enyaq_data.py
src/fhs_enyaq_data/loop.py
src/fhs_enyaq_data/mqtt.py
src/fhs_enyaq_data/output.py
src/fhs_enyaq_data.egg-info/PKG-INFO
src/fhs_enyaq_data.egg-info/SOURCES.txt
src/fhs_enyaq_data.egg-info/dependency_links.txt
src/fhs_enyaq_data.egg-info/entry_points.txt
src/fhs_enyaq_data.egg-info/requires.txt
src/fhs_enyaq_data.egg-info/top_level.txt
src/fhs_enyaq_data/abrp/__init__.py
src/fhs_enyaq_data/abrp/abrp_class.py
src/fhs_enyaq_data/skoda_class/__init__.py
src/fhs_enyaq_data/skoda_class/skoda_class.py
tests/test_sample.py