Metadata-Version: 2.1
Name: fhs-enyaq-data
Version: 0.1.5
Summary: enyaq car data
Home-page: https://github.com/foxhunt72/fhs-enyaq-data
Author: Richard de Vos
Author-email: rdevos72@gmail.com
License: MIT license
Classifier: Development Status :: 4 - Beta
Classifier: Programming Language :: Python
Classifier: Programming Language :: Python :: 3
Classifier: Programming Language :: Python :: 3.7
Classifier: Programming Language :: Python :: 3.8
Classifier: Programming Language :: Python :: 3.9
Classifier: Programming Language :: Python :: 3.10
Requires-Dist: skodaconnect
Requires-Dist: typer[all]
Requires-Dist: pyyaml
Requires-Dist: appdirs
Requires-Dist: requests
Requires-Dist: pyyaml
Requires-Dist: rich
Requires-Dist: paho-mqtt
